sputnik/__init__.py
sputnik/__main__.py
sputnik/about.py
sputnik/archive.py
sputnik/archive_reader.py
sputnik/archive_writer.py
sputnik/cache.py
sputnik/cached_package.py
sputnik/cli.py
sputnik/default.py
sputnik/dir_package.py
sputnik/index.py
sputnik/package.py
sputnik/package_list.py
sputnik/package_stub.py
sputnik/pool.py
sputnik/recipe.py
sputnik/session.py
sputnik/site.py
sputnik/uget.py
sputnik/util.py
sputnik/tests/__init__.py
sputnik/tests/conftest.py
sputnik/tests/test_archive.py
sputnik/tests/test_cache.py
sputnik/tests/test_constraint.py
sputnik/tests/test_package.py
sputnik/tests/test_remote.py
sputnik/tests/test_site.py
sputnik/tests/test_sputnik.py
sputnik-0.9.3.dist-info/DESCRIPTION.rst
sputnik-0.9.3.dist-info/METADATA
sputnik-0.9.3.dist-info/RECORD
sputnik-0.9.3.dist-info/WHEEL
sputnik-0.9.3.dist-info/entry_points.txt
sputnik-0.9.3.dist-info/metadata.json
sputnik-0.9.3.dist-info/top_level.txt
sputnik-0.9.3.dist-info/zip-safe
